setup.py
bhargavesh_dakka/__init__.py
bhargavesh_dakka/bhargavesh_dakka.py
bhargavesh_dakka.egg-info/PKG-INFO
bhargavesh_dakka.egg-info/SOURCES.txt
bhargavesh_dakka.egg-info/dependency_links.txt
bhargavesh_dakka.egg-info/not-zip-safe
bhargavesh_dakka.egg-info/top_level.txt