Metadata-Version: 2.1
Name: bhargavesh-dakka
Version: 0.3
Summary: Codes
Home-page: UNKNOWN
Author: Sare
Author-email: AiSir@vaddusami.com
License: UNKNOWN
Platform: UNKNOWN
